authx_core/__init__.py
authx_core/py.typed
authx_core/_async/__init__.py
authx_core/_async/_async_session.py
authx_core/database/__init__.py
authx_core/database/config.py
authx_core/database/setup.py
authx_core/engine/__init__.py
authx_core/engine/session.py
authx_core/engine/orm/__init__.py
authx_core/engine/orm/_base.py
authx_core/engine/orm/_fk.py
authx_core/engine/orm/_json.py
authx_core/engine/orm/_pk.py
authx_core/engine/orm/columns.py
authx_core/errors/__init__.py
authx_core/errors/_errors.py
authx_core/guid/__init__.py
authx_core/guid/_guide.py
authx_core/guid/type.py
authx_core/middleware/__init__.py
authx_core/middleware/_cpu.py
authx_core/middleware/_metric.py
authx_core/middleware/_middleware.py
authx_core/middleware/_record.py
authx_core/middleware/_stats.py
authx_core/model/__init__.py
authx_core/model/_model.py
authx_core/model/_settings.py
authx_core/routers/__init__.py
authx_core/routers/_inferring.py
authx_core/routers/_openapi.py
authx_core/settings/__init__.py
authx_core/settings/_backend.py
authx_core/settings/_base.py
authx_core/settings/_database.py
authx_core/utils/__init__.py
authx_core/utils/_cache.py
authx_core/utils/_camel.py
authx_core/utils/_enums.py
authx_core/utils/_task.py
authx_core/view/__init__.py
authx_core/view/_initial.py
authx_core/view/_update.py
authx_core/view/_view.py
authx_core-0.0.10.dist-info/LICENSE
authx_core-0.0.10.dist-info/WHEEL
authx_core-0.0.10.dist-info/METADATA
authx_core-0.0.10.dist-info/RECORD
